micropython_lsm6dsox/__init__.py
micropython_lsm6dsox/i2c_helpers.py
micropython_lsm6dsox/lsm6dsox.py
micropython_lsm6dsox-0.1.0.dist-info/LICENSE
micropython_lsm6dsox-0.1.0.dist-info/METADATA
micropython_lsm6dsox-0.1.0.dist-info/WHEEL
micropython_lsm6dsox-0.1.0.dist-info/top_level.txt
micropython_lsm6dsox-0.1.0.dist-info/RECORD
