Metadata-Version: 2.1
Name: micropython-lsm6dsox
Version: 0.1.0
Summary: MicroPython Library for the ST LSM6DSOX accelerometer/gyro Sensor
Author-email: JDM <xxyx@mailmeto.mozmail.com>
License: MIT
Project-URL: Homepage, https://github.com/jposada202020/MicroPython_LSM6DSOX
Keywords: sensor,micropython,lsm6dsox,accelerometer,micropython,lsm6dsox,st,gyro,driver,sensor
Classifier: Intended Audience :: Developers
Classifier: Topic :: Software Development :: Libraries
Classifier: Topic :: Software Development :: Embedded Systems
Classifier: Topic :: System :: Hardware
Classifier: License :: OSI Approved :: MIT License
Classifier: Programming Language :: Python :: Implementation :: MicroPython
License-File: LICENSE
